{
  "type" : "snapshot",
  "version" : 5,
  "expected" : {
    "protocol" : {
      "minReaderVersion" : 3,
      "minWriterVersion" : 7,
      "readerFeatures" : [ "deletionVectors", "columnMapping" ],
      "writerFeatures" : [ "deletionVectors", "checkConstraints", "generatedColumns", "invariants", "changeDataFeed", "appendOnly", "columnMapping" ]
    },
    "metadata" : {
      "format" : {
        "provider" : "parquet",
        "options" : { }
      },
      "schemaString" : "{\"type\":\"struct\",\"fields\":[{\"name\":\"id\",\"type\":\"integer\",\"nullable\":true,\"metadata\":{\"delta.columnMapping.id\":1,\"delta.columnMapping.physicalName\":\"col-5a0c5d19-b697-44d2-856b-e10fc1098ae4\"}},{\"name\":\"cat\",\"type\":\"string\",\"nullable\":true,\"metadata\":{\"delta.columnMapping.id\":2,\"delta.columnMapping.physicalName\":\"col-3e1fb708-526b-4128-a872-a04804d8d532\"}},{\"name\":\"value\",\"type\":\"integer\",\"nullable\":true,\"metadata\":{\"delta.columnMapping.id\":3,\"delta.columnMapping.physicalName\":\"col-4838ca25-0792-4015-a209-5a399a0eac67\"}}]}",
      "createdTime" : 1773118658865,
      "id" : "57f519f7-f1a1-468a-ba35-53f267e6887f",
      "partitionColumns" : [ "cat" ],
      "configuration" : {
        "delta.enableDeletionVectors" : "true",
        "delta.columnMapping.mode" : "name",
        "delta.columnMapping.maxColumnId" : "3"
      }
    }
  }
}