{
  "type" : "snapshot",
  "version" : 1,
  "expected" : {
    "protocol" : {
      "minReaderVersion" : 3,
      "minWriterVersion" : 7,
      "readerFeatures" : [ "deletionVectors", "variantType" ],
      "writerFeatures" : [ "deletionVectors", "variantType", "appendOnly", "invariants" ]
    },
    "metadata" : {
      "format" : {
        "provider" : "parquet",
        "options" : { }
      },
      "schemaString" : "{\"type\":\"struct\",\"fields\":[{\"name\":\"id\",\"type\":\"integer\",\"nullable\":true,\"metadata\":{}},{\"name\":\"data\",\"type\":\"variant\",\"nullable\":true,\"metadata\":{}}]}",
      "createdTime" : 1773119229635,
      "id" : "b0b0df4d-656d-49a8-8f94-4dc405cb9f6a",
      "partitionColumns" : [ ],
      "configuration" : {
        "delta.enableDeletionVectors" : "true"
      }
    }
  }
}