{"commitInfo":{"timestamp":1773118518359,"operation":"UPDATE","operationParameters":{"predicate":"[\"(id#12003L < 3)\"]"},"readVersion":1,"isolationLevel":"WriteSerializable","isBlindAppend":false,"operationMetrics":{"numRemovedFiles":"1","numRemovedBytes":"504","numCopiedRows":"0","numDeletionVectorsAdded":"1","numDeletionVectorsRemoved":"0","numAddedChangeFiles":"0","executionTimeMs":"1731","numDeletionVectorsUpdated":"0","scanTimeMs":"758","numAddedFiles":"1","numUpdatedRows":"3","numAddedBytes":"1316","rewriteTimeMs":"964"},"tags":{"noRowsCopied":"true","delta.rowTracking.preserved":"true","restoresDeletedRows":"false"},"engineInfo":"Databricks-Runtime/<unknown>","txnId":"6a636bca-3b1d-422f-a9bb-d501301bd7ee"}}
{"remove":{"path":"test%25file%25prefix-part-00000-0243e9c6-a966-4d5d-aba8-77889198bcbc-c000.snappy.parquet","deletionTimestamp":1773118518249,"dataChange":true,"extendedFileMetadata":true,"partitionValues":{},"size":504,"tags":{"INSERTION_TIME":"1773118515169000","MIN_INSERTION_TIME":"1773118515169000","MAX_INSERTION_TIME":"1773118515169000","OPTIMIZE_TARGET_SIZE":"268435456"},"baseRowId":0,"defaultRowCommitVersion":0,"stats":"{\"numRecords\":2}"}}
{"remove":{"path":"test%25file%25prefix-part-00001-884cc04b-08e5-4a79-8248-4936ba249d41-c000.snappy.parquet","deletionTimestamp":1773118518249,"dataChange":true,"extendedFileMetadata":true,"partitionValues":{},"size":509,"tags":{"INSERTION_TIME":"1773118515169001","MIN_INSERTION_TIME":"1773118515169001","MAX_INSERTION_TIME":"1773118515169001","OPTIMIZE_TARGET_SIZE":"268435456"},"baseRowId":2,"defaultRowCommitVersion":0,"stats":"{\"numRecords\":3,\"minValues\":{\"id\":2},\"maxValues\":{\"id\":4},\"nullCount\":{\"id\":0},\"tightBounds\":false}"}}
{"add":{"path":"test%25file%25prefix-part-00000-eda78453-3cc2-4afd-903c-18b700813939-c000.snappy.parquet","partitionValues":{},"size":1316,"modificationTime":1773118517549,"dataChange":true,"stats":"{\"numRecords\":3,\"minValues\":{\"id\":100},\"maxValues\":{\"id\":102},\"nullCount\":{\"id\":0},\"tightBounds\":true}","tags":{"MAX_INSERTION_TIME":"1773118515169000","INSERTION_TIME":"1773118515169000","MIN_INSERTION_TIME":"1773118515169000","OPTIMIZE_TARGET_SIZE":"268435456"},"baseRowId":10,"defaultRowCommitVersion":2}}
{"add":{"path":"test%25file%25prefix-part-00001-884cc04b-08e5-4a79-8248-4936ba249d41-c000.snappy.parquet","partitionValues":{},"size":509,"modificationTime":1773118515169,"dataChange":true,"stats":"{\"numRecords\":3,\"minValues\":{\"id\":2},\"maxValues\":{\"id\":4},\"nullCount\":{\"id\":0},\"tightBounds\":false}","tags":{"INSERTION_TIME":"1773118515169001","MIN_INSERTION_TIME":"1773118515169001","MAX_INSERTION_TIME":"1773118515169001","OPTIMIZE_TARGET_SIZE":"268435456"},"deletionVector":{"storageType":"u","pathOrInlineDv":"pG@uEmsmH.VNzK1.zB(#","offset":1,"sizeInBytes":34,"cardinality":1},"baseRowId":2,"defaultRowCommitVersion":0}}
{"domainMetadata":{"domain":"delta.rowTracking","configuration":"{\"rowIdHighWaterMark\":12,\"domainName\":\"delta.rowTracking\"}","removed":false}}
