{"commitInfo":{"timestamp":1773115015293,"operation":"WRITE","operationParameters":{"mode":"Append","statsOnLoad":false,"partitionBy":"[]"},"readVersion":1,"isolationLevel":"WriteSerializable","isBlindAppend":true,"operationMetrics":{"numFiles":"1","numOutputRows":"1","numOutputBytes":"758"},"tags":{"noRowsCopied":"true","restoresDeletedRows":"false"},"engineInfo":"Databricks-Runtime/<unknown>","txnId":"823be091-5047-4c43-ba20-9b4c443ec603"}}
{"add":{"path":"test%25file%25prefix-part-00000-bcb7691c-2d34-4d07-b780-2b9d6b44391e-c000.snappy.parquet","partitionValues":{},"size":758,"modificationTime":1773115015220,"dataChange":true,"stats":"{\"numRecords\":1,\"minValues\":{\"id\":1,\"event_time\":\"09:00:00\"},\"maxValues\":{\"id\":1,\"event_time\":\"09:00:00\"},\"nullCount\":{\"id\":0,\"event_time\":0},\"tightBounds\":true}","tags":{"INSERTION_TIME":"1773115015220000","MIN_INSERTION_TIME":"1773115015220000","MAX_INSERTION_TIME":"1773115015220000","OPTIMIZE_TARGET_SIZE":"268435456"}}}
