{
  "type" : "snapshot",
  "version" : 2,
  "expected" : {
    "protocol" : {
      "minReaderVersion" : 3,
      "minWriterVersion" : 7,
      "readerFeatures" : [ "deletionVectors" ],
      "writerFeatures" : [ "deletionVectors", "appendOnly", "invariants" ]
    },
    "metadata" : {
      "format" : {
        "provider" : "parquet",
        "options" : { }
      },
      "schemaString" : "{\"type\":\"struct\",\"fields\":[{\"name\":\"id\",\"type\":\"integer\",\"nullable\":true,\"metadata\":{}},{\"name\":\"value\",\"type\":\"string\",\"nullable\":true,\"metadata\":{}},{\"name\":\"amount\",\"type\":\"integer\",\"nullable\":true,\"metadata\":{}}]}",
      "createdTime" : 1773117939715,
      "id" : "ac6827bd-37a1-499b-9493-b33df510b20c",
      "partitionColumns" : [ ],
      "configuration" : {
        "delta.enableDeletionVectors" : "true"
      }
    }
  }
}