{"commitInfo":{"timestamp":1773116882727,"operation":"WRITE","operationParameters":{"mode":"ErrorIfExists","statsOnLoad":false,"partitionBy":"[]"},"isolationLevel":"WriteSerializable","isBlindAppend":true,"operationMetrics":{"numFiles":"2","numOutputRows":"10","numOutputBytes":"1039"},"tags":{"noRowsCopied":"true","restoresDeletedRows":"false"},"engineInfo":"Databricks-Runtime/<unknown>","txnId":"d42c32b2-fcc0-4a44-a716-bc7dae0fa2b8"}}
{"metaData":{"id":"65134bd2-a56c-4ebd-820f-75ea8785a162","format":{"provider":"parquet","options":{}},"schemaString":"{\"type\":\"struct\",\"fields\":[{\"name\":\"id\",\"type\":\"long\",\"nullable\":true,\"metadata\":{}}]}","partitionColumns":[],"configuration":{"delta.enableDeletionVectors":"true"},"createdTime":1773116882586}}
{"protocol":{"minReaderVersion":3,"minWriterVersion":7,"readerFeatures":["deletionVectors"],"writerFeatures":["deletionVectors","appendOnly","invariants"]}}
{"add":{"path":"test%25file%25prefix-part-00000-e3805bcf-4217-4354-8fcd-46d324678985-c000.snappy.parquet","partitionValues":{},"size":518,"modificationTime":1773116882669,"dataChange":true,"stats":"{\"numRecords\":5,\"minValues\":{\"id\":0},\"maxValues\":{\"id\":4},\"nullCount\":{\"id\":0},\"tightBounds\":true}","tags":{"INSERTION_TIME":"1773116882669000","MIN_INSERTION_TIME":"1773116882669000","MAX_INSERTION_TIME":"1773116882669000","OPTIMIZE_TARGET_SIZE":"268435456"}}}
{"add":{"path":"test%25file%25prefix-part-00001-5e371b3f-530e-47a1-8f11-48fe6d136677-c000.snappy.parquet","partitionValues":{},"size":521,"modificationTime":1773116882669,"dataChange":true,"stats":"{\"numRecords\":5,\"minValues\":{\"id\":5},\"maxValues\":{\"id\":9},\"nullCount\":{\"id\":0},\"tightBounds\":true}","tags":{"INSERTION_TIME":"1773116882669001","MIN_INSERTION_TIME":"1773116882669001","MAX_INSERTION_TIME":"1773116882669001","OPTIMIZE_TARGET_SIZE":"268435456"}}}
