{"commitInfo":{"timestamp":1773116096813,"operation":"WRITE","operationParameters":{"mode":"Overwrite","statsOnLoad":false,"partitionBy":"[]"},"isolationLevel":"WriteSerializable","isBlindAppend":false,"operationMetrics":{"numFiles":"2","numRemovedFiles":"0","numRemovedBytes":"0","numDeletionVectorsRemoved":"0","numOutputRows":"10","numOutputBytes":"1039"},"tags":{"noRowsCopied":"true","restoresDeletedRows":"false"},"engineInfo":"Databricks-Runtime/<unknown>","txnId":"ca06657f-ab3d-4359-ac1c-9421b1374bd6"}}
{"metaData":{"id":"b967df14-3ff9-4bac-b314-c02d7c6273d5","format":{"provider":"parquet","options":{}},"schemaString":"{\"type\":\"struct\",\"fields\":[{\"name\":\"id\",\"type\":\"long\",\"nullable\":true,\"metadata\":{}}]}","partitionColumns":[],"configuration":{"delta.enableDeletionVectors":"true"},"createdTime":1773116096516}}
{"protocol":{"minReaderVersion":3,"minWriterVersion":7,"readerFeatures":["deletionVectors"],"writerFeatures":["deletionVectors","appendOnly","invariants"]}}
{"add":{"path":"test%25file%25prefix-part-00000-d447d370-5485-4cb8-9033-a3b314eb6c27-c000.snappy.parquet","partitionValues":{},"size":518,"modificationTime":1773116096600,"dataChange":true,"stats":"{\"numRecords\":5,\"minValues\":{\"id\":0},\"maxValues\":{\"id\":4},\"nullCount\":{\"id\":0},\"tightBounds\":true}","tags":{"INSERTION_TIME":"1773116096600000","MIN_INSERTION_TIME":"1773116096600000","MAX_INSERTION_TIME":"1773116096600000","OPTIMIZE_TARGET_SIZE":"268435456"}}}
{"add":{"path":"test%25file%25prefix-part-00001-e9308fc8-4311-4857-b286-9ff7e548e4ba-c000.snappy.parquet","partitionValues":{},"size":521,"modificationTime":1773116096600,"dataChange":true,"stats":"{\"numRecords\":5,\"minValues\":{\"id\":5},\"maxValues\":{\"id\":9},\"nullCount\":{\"id\":0},\"tightBounds\":true}","tags":{"INSERTION_TIME":"1773116096600001","MIN_INSERTION_TIME":"1773116096600001","MAX_INSERTION_TIME":"1773116096600001","OPTIMIZE_TARGET_SIZE":"268435456"}}}
