{
  "type" : "snapshot",
  "version" : 2,
  "expected" : {
    "protocol" : {
      "minReaderVersion" : 3,
      "minWriterVersion" : 7,
      "readerFeatures" : [ "deletionVectors", "variantType" ],
      "writerFeatures" : [ "deletionVectors", "variantType", "appendOnly", "invariants" ]
    },
    "metadata" : {
      "format" : {
        "provider" : "parquet",
        "options" : { }
      },
      "schemaString" : "{\"type\":\"struct\",\"fields\":[{\"name\":\"id\",\"type\":\"integer\",\"nullable\":true,\"metadata\":{}},{\"name\":\"payload\",\"type\":\"variant\",\"nullable\":true,\"metadata\":{}}]}",
      "createdTime" : 1773119210306,
      "id" : "9f4d6df7-6191-4abe-b636-274b2a151cce",
      "partitionColumns" : [ ],
      "configuration" : {
        "delta.enableDeletionVectors" : "true"
      }
    }
  }
}