{"commitInfo":{"timestamp":1773115948789,"operation":"WRITE","operationParameters":{"mode":"ErrorIfExists","statsOnLoad":false,"partitionBy":"[]"},"isolationLevel":"WriteSerializable","isBlindAppend":true,"operationMetrics":{"numFiles":"1","numOutputRows":"3","numOutputBytes":"1000"},"tags":{"noRowsCopied":"true","restoresDeletedRows":"false"},"engineInfo":"Databricks-Runtime/<unknown>","txnId":"fe0084b1-5e34-471a-857d-47fa9e0fb6db"}}
{"metaData":{"id":"8b2e708e-008f-438a-a738-9189539a3433","format":{"provider":"parquet","options":{}},"schemaString":"{\"type\":\"struct\",\"fields\":[{\"name\":\"a\",\"type\":\"long\",\"nullable\":true,\"metadata\":{}},{\"name\":\"b\",\"type\":\"string\",\"nullable\":true,\"metadata\":{}},{\"name\":\"c\",\"type\":\"double\",\"nullable\":true,\"metadata\":{}}]}","partitionColumns":[],"configuration":{"delta.enableDeletionVectors":"true"},"createdTime":1773115948613}}
{"protocol":{"minReaderVersion":3,"minWriterVersion":7,"readerFeatures":["deletionVectors"],"writerFeatures":["deletionVectors","appendOnly","invariants"]}}
{"add":{"path":"test%25file%25prefix-part-00000-06a9aadf-fed1-4b09-bcec-f4a240c0b964-c000.snappy.parquet","partitionValues":{},"size":1000,"modificationTime":1773115948730,"dataChange":true,"stats":"{\"numRecords\":3,\"minValues\":{\"a\":1,\"b\":\"hello\",\"c\":10.0},\"maxValues\":{\"a\":3,\"b\":\"world\",\"c\":30.0},\"nullCount\":{\"a\":0,\"b\":0,\"c\":0},\"tightBounds\":true}","tags":{"INSERTION_TIME":"1773115948730000","MIN_INSERTION_TIME":"1773115948730000","MAX_INSERTION_TIME":"1773115948730000","OPTIMIZE_TARGET_SIZE":"268435456"}}}
