{"commitInfo":{"timestamp":1773115316058,"operation":"WRITE","operationParameters":{"mode":"ErrorIfExists","statsOnLoad":false,"partitionBy":"[]"},"isolationLevel":"WriteSerializable","isBlindAppend":true,"operationMetrics":{"numFiles":"1","numOutputRows":"50","numOutputBytes":"676"},"tags":{"noRowsCopied":"true","restoresDeletedRows":"false"},"engineInfo":"Databricks-Runtime/<unknown>","txnId":"34a77f01-2c14-4c7b-bae3-6ae64a34f4d6"}}
{"metaData":{"id":"3c056d43-94a4-428f-a075-ca7fd7c2130e","format":{"provider":"parquet","options":{}},"schemaString":"{\"type\":\"struct\",\"fields\":[{\"name\":\"id\",\"type\":\"integer\",\"nullable\":true,\"metadata\":{}}]}","partitionColumns":[],"configuration":{"delta.enableDeletionVectors":"true"},"createdTime":1773115315859}}
{"protocol":{"minReaderVersion":3,"minWriterVersion":7,"readerFeatures":["deletionVectors"],"writerFeatures":["deletionVectors","appendOnly","invariants"]}}
{"add":{"path":"test%25file%25prefix-part-00000-d9157f28-d54a-4598-b0f7-d922cf0602cc-c000.snappy.parquet","partitionValues":{},"size":676,"modificationTime":1773115315964,"dataChange":true,"stats":"{\"numRecords\":50,\"minValues\":{\"id\":1},\"maxValues\":{\"id\":50},\"nullCount\":{\"id\":0},\"tightBounds\":true}","tags":{"INSERTION_TIME":"1773115315964000","MIN_INSERTION_TIME":"1773115315964000","MAX_INSERTION_TIME":"1773115315964000","OPTIMIZE_TARGET_SIZE":"268435456"}}}
