{"commitInfo":{"timestamp":1773118426202,"operation":"WRITE","operationParameters":{"mode":"Append","statsOnLoad":false,"partitionBy":"[]"},"readVersion":37,"isolationLevel":"WriteSerializable","isBlindAppend":true,"operationMetrics":{"numFiles":"1","numOutputRows":"1","numOutputBytes":"496"},"tags":{"noRowsCopied":"true","restoresDeletedRows":"false"},"engineInfo":"Databricks-Runtime/<unknown>","txnId":"752a41fe-0adc-4c25-88e8-9482581523e3"}}
{"add":{"path":"test%25file%25prefix-part-00000-a5093e43-60aa-47b8-a3a0-595d3a1747ff-c000.snappy.parquet","partitionValues":{},"size":496,"modificationTime":1773118426130,"dataChange":true,"stats":"{\"numRecords\":1,\"minValues\":{\"id\":38},\"maxValues\":{\"id\":38},\"nullCount\":{\"id\":0},\"tightBounds\":true}","tags":{"INSERTION_TIME":"1773118426130000","MIN_INSERTION_TIME":"1773118426130000","MAX_INSERTION_TIME":"1773118426130000","OPTIMIZE_TARGET_SIZE":"268435456"}}}
