{"commitInfo":{"timestamp":1773118421196,"operation":"WRITE","operationParameters":{"mode":"Append","statsOnLoad":false,"partitionBy":"[]"},"readVersion":29,"isolationLevel":"WriteSerializable","isBlindAppend":true,"operationMetrics":{"numFiles":"1","numOutputRows":"1","numOutputBytes":"495"},"tags":{"noRowsCopied":"true","restoresDeletedRows":"false"},"engineInfo":"Databricks-Runtime/<unknown>","txnId":"08a43549-cce3-4b8b-a6fa-2579eb47cf65"}}
{"add":{"path":"test%25file%25prefix-part-00000-51255d5d-5672-4c98-af4f-c5b29eb0d431-c000.snappy.parquet","partitionValues":{},"size":495,"modificationTime":1773118421122,"dataChange":true,"stats":"{\"numRecords\":1,\"minValues\":{\"id\":30},\"maxValues\":{\"id\":30},\"nullCount\":{\"id\":0},\"tightBounds\":true}","tags":{"INSERTION_TIME":"1773118421122000","MIN_INSERTION_TIME":"1773118421122000","MAX_INSERTION_TIME":"1773118421122000","OPTIMIZE_TARGET_SIZE":"268435456"}}}
