{"commitInfo":{"timestamp":1773119168045,"operation":"WRITE","operationParameters":{"mode":"Append","statsOnLoad":false,"partitionBy":"[]"},"readVersion":3,"isolationLevel":"WriteSerializable","isBlindAppend":true,"operationMetrics":{"numFiles":"1","numOutputRows":"1","numOutputBytes":"938"},"tags":{"noRowsCopied":"true","restoresDeletedRows":"false"},"engineInfo":"Databricks-Runtime/<unknown>","txnId":"73deb15a-5f30-4e56-be6c-51fdb39b6fbc"}}
{"add":{"path":"part=2/test%25file%25prefix-part-00000-45ed0bdd-8139-4c12-aa85-db7beb78ff2d.c000.snappy.parquet","partitionValues":{"part":"2"},"size":938,"modificationTime":1773119167959,"dataChange":true,"stats":"{\"numRecords\":1,\"nullCount\":{\"v\":0},\"tightBounds\":true}","tags":{"MAX_INSERTION_TIME":"1773119167959000","INSERTION_TIME":"1773119167959000","SHREDDING_STATE":"0","MIN_INSERTION_TIME":"1773119167959000","OPTIMIZE_TARGET_SIZE":"268435456"}}}
