{"commitInfo":{"timestamp":1773115006041,"operation":"CREATE TABLE","operationParameters":{"partitionBy":"[]","clusterBy":"[]","description":null,"isManaged":"false","properties":"{\"delta.enableDeletionVectors\":\"true\"}","statsOnLoad":false},"isolationLevel":"WriteSerializable","isBlindAppend":true,"operationMetrics":{},"tags":{"restoresDeletedRows":"false"},"engineInfo":"Databricks-Runtime/<unknown>","txnId":"fb943e08-72a8-4e8f-8fd3-24998ab9b619"}}
{"metaData":{"id":"9e8e34fc-dea8-4c80-b5c6-e20428a68eff","format":{"provider":"parquet","options":{}},"schemaString":"{\"type\":\"struct\",\"fields\":[{\"name\":\"id\",\"type\":\"integer\",\"nullable\":true,\"metadata\":{}},{\"name\":\"required_field\",\"type\":\"string\",\"nullable\":true,\"metadata\":{}}]}","partitionColumns":[],"configuration":{"delta.enableDeletionVectors":"true"},"createdTime":1773115005984}}
{"protocol":{"minReaderVersion":3,"minWriterVersion":7,"readerFeatures":["deletionVectors"],"writerFeatures":["deletionVectors","appendOnly","invariants"]}}
