{
  "name" : "cp_schema_evolution",
  "description" : "Checkpoint with schema evolution",
  "schema" : {
    "type" : "struct",
    "fields" : [ {
      "name" : "id",
      "type" : "long",
      "nullable" : true,
      "metadata" : { }
    }, {
      "name" : "name",
      "type" : "string",
      "nullable" : true,
      "metadata" : { }
    } ]
  },
  "protocol" : {
    "minReaderVersion" : 3,
    "minWriterVersion" : 7,
    "readerFeatures" : [ "deletionVectors" ],
    "writerFeatures" : [ "appendOnly", "deletionVectors", "invariants" ]
  },
  "logInfo" : {
    "numAddFiles" : 4,
    "numRemoveFiles" : 0,
    "sizeInBytes" : 2985,
    "numCommits" : 2,
    "numActions" : 10,
    "lastCheckpointVersion" : 0,
    "lastCrcVersion" : 2,
    "numParallelCheckpointFiles" : 1
  },
  "properties" : {
    "delta.enableDeletionVectors" : "true"
  },
  "dataLayout" : {
    "numClusteringColumns" : 0,
    "numPartitionColumns" : 0,
    "numDistinctPartitions" : 0
  }
}