{"commitInfo":{"timestamp":1775089639111,"operation":"CREATE TABLE","operationParameters":{"partitionBy":"[\"part\"]","clusterBy":"[]","description":null,"isManaged":"true","properties":"{}"},"isolationLevel":"Serializable","isBlindAppend":true,"operationMetrics":{},"engineInfo":"Apache-Spark/3.5.3 Delta-Lake/3.3.2","txnId":"e8f4ed3c-9add-4c50-98a6-fd6946ac980e"}}
{"metaData":{"id":"9dcbf06c-d59a-441c-8213-20ff9dc00afa","format":{"provider":"parquet","options":{}},"schemaString":"{\"type\":\"struct\",\"fields\":[{\"name\":\"id\",\"type\":\"long\",\"nullable\":true,\"metadata\":{}},{\"name\":\"part\",\"type\":\"integer\",\"nullable\":true,\"metadata\":{}}]}","partitionColumns":["part"],"configuration":{},"createdTime":1775089639095}}
{"protocol":{"minReaderVersion":1,"minWriterVersion":2}}
