{"commitInfo":{"timestamp":1773118071646,"operation":"MERGE","operationParameters":{"predicate":"[\"((id#158634 = id#158625) AND (key#158635 = key#158626))\"]","clusterBy":"[]","matchedPredicates":"[{\"actionType\":\"update\"}]","statsOnLoad":false,"notMatchedBySourcePredicates":"[]","notMatchedPredicates":"[{\"actionType\":\"insert\"}]"},"readVersion":0,"isolationLevel":"WriteSerializable","isBlindAppend":false,"operationMetrics":{"numTargetRowsCopied":"0","numTargetRowsDeleted":"0","numTargetFilesAdded":"2","numTargetBytesAdded":"1845","numTargetBytesRemoved":"0","numTargetDeletionVectorsAdded":"1","numTargetRowsMatchedUpdated":"1","executionTimeMs":"815","materializeSourceTimeMs":"38","numTargetRowsInserted":"2","numTargetRowsMatchedDeleted":"0","numTargetDeletionVectorsUpdated":"0","scanTimeMs":"410","numTargetRowsUpdated":"1","numOutputRows":"3","numTargetDeletionVectorsRemoved":"0","numTargetRowsNotMatchedBySourceUpdated":"0","numTargetChangeFilesAdded":"0","numSourceRows":"3","numTargetFilesRemoved":"0","numTargetRowsNotMatchedBySourceDeleted":"0","rewriteTimeMs":"362"},"tags":{"noRowsCopied":"true","delta.rowTracking.preserved":"false","restoresDeletedRows":"false"},"engineInfo":"Databricks-Runtime/<unknown>","txnId":"747c8359-61e4-4c66-97f0-fd36a6a45d54"}}
{"remove":{"path":"test%25file%25prefix-part-00000-228212bc-94b0-4d87-8bf4-6e476aa3d049-c000.snappy.parquet","deletionTimestamp":1773118071546,"dataChange":true,"extendedFileMetadata":true,"partitionValues":{},"size":939,"tags":{"INSERTION_TIME":"1773118070191000","MIN_INSERTION_TIME":"1773118070191000","MAX_INSERTION_TIME":"1773118070191000","OPTIMIZE_TARGET_SIZE":"268435456"},"stats":"{\"numRecords\":3,\"minValues\":{\"id\":1,\"key\":\"a\",\"amount\":100},\"maxValues\":{\"id\":3,\"key\":\"c\",\"amount\":300},\"nullCount\":{\"id\":0,\"key\":0,\"amount\":0},\"tightBounds\":false}"}}
{"add":{"path":"test%25file%25prefix-part-00000-92fd1bc7-4fff-4688-9d9c-2b8418e36dd6-c000.snappy.parquet","partitionValues":{},"size":919,"modificationTime":1773118071531,"dataChange":true,"stats":"{\"numRecords\":1,\"minValues\":{\"id\":2,\"key\":\"b\",\"amount\":999},\"maxValues\":{\"id\":2,\"key\":\"b\",\"amount\":999},\"nullCount\":{\"id\":0,\"key\":0,\"amount\":0},\"tightBounds\":true}","tags":{"INSERTION_TIME":"1773118071531000","MIN_INSERTION_TIME":"1773118070191000","MAX_INSERTION_TIME":"1773118071531000","OPTIMIZE_TARGET_SIZE":"268435456"}}}
{"add":{"path":"test%25file%25prefix-part-00001-56399bf9-d8e4-4035-98d7-20bf5d9714ed-c000.snappy.parquet","partitionValues":{},"size":926,"modificationTime":1773118071531,"dataChange":true,"stats":"{\"numRecords\":2,\"minValues\":{\"id\":3,\"key\":\"d\",\"amount\":400},\"maxValues\":{\"id\":4,\"key\":\"x\",\"amount\":888},\"nullCount\":{\"id\":0,\"key\":0,\"amount\":0},\"tightBounds\":true}","tags":{"INSERTION_TIME":"1773118071531001","MIN_INSERTION_TIME":"1773118070191000","MAX_INSERTION_TIME":"1773118071531001","OPTIMIZE_TARGET_SIZE":"268435456"}}}
{"add":{"path":"test%25file%25prefix-part-00000-228212bc-94b0-4d87-8bf4-6e476aa3d049-c000.snappy.parquet","partitionValues":{},"size":939,"modificationTime":1773118070191,"dataChange":true,"stats":"{\"numRecords\":3,\"minValues\":{\"id\":1,\"key\":\"a\",\"amount\":100},\"maxValues\":{\"id\":3,\"key\":\"c\",\"amount\":300},\"nullCount\":{\"id\":0,\"key\":0,\"amount\":0},\"tightBounds\":false}","tags":{"INSERTION_TIME":"1773118070191000","MIN_INSERTION_TIME":"1773118070191000","MAX_INSERTION_TIME":"1773118070191000","OPTIMIZE_TARGET_SIZE":"268435456"},"deletionVector":{"storageType":"u","pathOrInlineDv":"E)BCbvZnqRT7jdQ5Dgld","offset":1,"sizeInBytes":34,"cardinality":1}}}
