{
  "type" : "snapshotConstruction",
  "version" : 1,
  "expected" : {
    "version" : 1,
    "protocol" : {
      "minReaderVersion" : 1,
      "minWriterVersion" : 2
    },
    "metadata" : {
      "format" : {
        "provider" : "parquet",
        "options" : { }
      },
      "schemaString" : "{\"type\":\"struct\",\"fields\":[{\"name\":\"id\",\"type\":\"long\",\"nullable\":true,\"metadata\":{}},{\"name\":\"part\",\"type\":\"integer\",\"nullable\":true,\"metadata\":{}}]}",
      "partitionColumns" : [ "part" ],
      "configuration" : { },
      "createdTime" : 1775089600315,
      "id" : "e1724749-ec30-4366-abdf-67d55273e402"
    }
  }
}