{
  "type" : "snapshot",
  "version" : 3,
  "expected" : {
    "protocol" : {
      "minReaderVersion" : 3,
      "minWriterVersion" : 7,
      "readerFeatures" : [ "deletionVectors" ],
      "writerFeatures" : [ "deletionVectors", "appendOnly", "invariants" ]
    },
    "metadata" : {
      "format" : {
        "provider" : "parquet",
        "options" : { }
      },
      "schemaString" : "{\"type\":\"struct\",\"fields\":[{\"name\":\"id\",\"type\":\"integer\",\"nullable\":true,\"metadata\":{}},{\"name\":\"data\",\"type\":\"binary\",\"nullable\":true,\"metadata\":{}}]}",
      "createdTime" : 1773115760766,
      "id" : "c8510908-983b-4018-80ef-7b1625f89df4",
      "partitionColumns" : [ ],
      "configuration" : {
        "delta.enableDeletionVectors" : "true"
      }
    }
  }
}