{
  "type" : "snapshot",
  "version" : 1,
  "expected" : {
    "protocol" : {
      "minReaderVersion" : 3,
      "minWriterVersion" : 7,
      "readerFeatures" : [ "deletionVectors" ],
      "writerFeatures" : [ "deletionVectors", "appendOnly", "invariants" ]
    },
    "metadata" : {
      "format" : {
        "provider" : "parquet",
        "options" : { }
      },
      "schemaString" : "{\"type\":\"struct\",\"fields\":[{\"name\":\"id\",\"type\":\"integer\",\"nullable\":true,\"metadata\":{}},{\"name\":\"value\",\"type\":\"string\",\"nullable\":true,\"metadata\":{}},{\"name\":\"bonus\",\"type\":\"string\",\"nullable\":true,\"metadata\":{}}]}",
      "createdTime" : 1773118008558,
      "id" : "1cdbc1b1-85bb-46eb-842a-016f7311ba86",
      "partitionColumns" : [ ],
      "configuration" : {
        "delta.enableDeletionVectors" : "true"
      }
    }
  }
}