{"commitInfo":{"timestamp":1773115536585,"operation":"WRITE","operationParameters":{"mode":"Append","statsOnLoad":false,"partitionBy":"[]"},"readVersion":1,"isolationLevel":"WriteSerializable","isBlindAppend":true,"operationMetrics":{"numFiles":"1","numOutputRows":"1","numOutputBytes":"910"},"tags":{"noRowsCopied":"true","restoresDeletedRows":"false"},"engineInfo":"Databricks-Runtime/<unknown>","txnId":"c6e957b8-1bae-4ec6-a258-c343132481aa"}}
{"add":{"path":"UN/test%25file%25prefix-part-00000-ea6606eb-950c-4070-b9e5-104173a3ece4-c000.snappy.parquet","partitionValues":{},"size":910,"modificationTime":1773115536508,"dataChange":true,"stats":"{\"numRecords\":1,\"minValues\":{\"id\":3,\"value\":\"after1\"},\"maxValues\":{\"id\":3,\"value\":\"after1\"},\"nullCount\":{\"id\":0,\"value\":0},\"tightBounds\":true}","tags":{"INSERTION_TIME":"1773115536508000","MIN_INSERTION_TIME":"1773115536508000","MAX_INSERTION_TIME":"1773115536508000","OPTIMIZE_TARGET_SIZE":"268435456"}}}
