{"commitInfo":{"timestamp":1773118394378,"operation":"WRITE","operationParameters":{"mode":"Overwrite","statsOnLoad":false,"partitionBy":"[]"},"readVersion":0,"isolationLevel":"WriteSerializable","isBlindAppend":false,"operationMetrics":{"numFiles":"2","numRemovedFiles":"2","numRemovedBytes":"1039","numDeletionVectorsRemoved":"0","numOutputRows":"20","numOutputBytes":"1091"},"tags":{"noRowsCopied":"true","restoresDeletedRows":"false"},"engineInfo":"Databricks-Runtime/<unknown>","txnId":"80952290-0e9b-4ec3-8a0a-a707e2770fe3"}}
{"add":{"path":"test%25file%25prefix-part-00000-60e9909e-ae72-45bd-a607-37739128b263-c000.snappy.parquet","partitionValues":{},"size":546,"modificationTime":1773118394135,"dataChange":true,"stats":"{\"numRecords\":10,\"minValues\":{\"id\":0},\"maxValues\":{\"id\":9},\"nullCount\":{\"id\":0},\"tightBounds\":true}","tags":{"INSERTION_TIME":"1773118394135000","MIN_INSERTION_TIME":"1773118394135000","MAX_INSERTION_TIME":"1773118394135000","OPTIMIZE_TARGET_SIZE":"268435456"}}}
{"add":{"path":"test%25file%25prefix-part-00001-1ed4c4b0-6d9c-461c-b64c-46e26ffdabb7-c000.snappy.parquet","partitionValues":{},"size":545,"modificationTime":1773118394135,"dataChange":true,"stats":"{\"numRecords\":10,\"minValues\":{\"id\":10},\"maxValues\":{\"id\":19},\"nullCount\":{\"id\":0},\"tightBounds\":true}","tags":{"INSERTION_TIME":"1773118394135001","MIN_INSERTION_TIME":"1773118394135001","MAX_INSERTION_TIME":"1773118394135001","OPTIMIZE_TARGET_SIZE":"268435456"}}}
{"remove":{"path":"test%25file%25prefix-part-00000-79066ecb-8f09-46e2-9441-9d8cde0b720e-c000.snappy.parquet","deletionTimestamp":1773118394306,"dataChange":true,"extendedFileMetadata":true,"partitionValues":{},"size":518,"tags":{"INSERTION_TIME":"1773118393415000","MIN_INSERTION_TIME":"1773118393415000","MAX_INSERTION_TIME":"1773118393415000","OPTIMIZE_TARGET_SIZE":"268435456"}}}
{"remove":{"path":"test%25file%25prefix-part-00001-6c134a7c-6b88-4493-b1f3-5f07dafd1c4d-c000.snappy.parquet","deletionTimestamp":1773118394307,"dataChange":true,"extendedFileMetadata":true,"partitionValues":{},"size":521,"tags":{"INSERTION_TIME":"1773118393415001","MIN_INSERTION_TIME":"1773118393415001","MAX_INSERTION_TIME":"1773118393415001","OPTIMIZE_TARGET_SIZE":"268435456"}}}
