{"commitInfo":{"timestamp":1773117753435,"operation":"WRITE","operationParameters":{"mode":"ErrorIfExists","statsOnLoad":false,"partitionBy":"[]"},"isolationLevel":"WriteSerializable","isBlindAppend":true,"operationMetrics":{"numFiles":"1","numOutputRows":"2","numOutputBytes":"697"},"tags":{"noRowsCopied":"true","restoresDeletedRows":"false"},"engineInfo":"Databricks-Runtime/<unknown>","txnId":"e831bbcc-200f-4b32-b519-2ccd8d5ce8b1"}}
{"metaData":{"id":"567692e2-c43c-4fb9-932c-bf3969bae145","format":{"provider":"parquet","options":{}},"schemaString":"{\"type\":\"struct\",\"fields\":[{\"name\":\"id\",\"type\":\"integer\",\"nullable\":true,\"metadata\":{}},{\"name\":\"value\",\"type\":\"string\",\"nullable\":true,\"metadata\":{}}]}","partitionColumns":[],"configuration":{"delta.enableDeletionVectors":"true"},"createdTime":1773117753218}}
{"protocol":{"minReaderVersion":3,"minWriterVersion":7,"readerFeatures":["deletionVectors"],"writerFeatures":["deletionVectors","appendOnly","invariants"]}}
{"add":{"path":"test%25file%25prefix-part-00000-58212860-40c2-4abb-b008-c2815d9d6e64-c000.snappy.parquet","partitionValues":{},"size":697,"modificationTime":1773117753348,"dataChange":true,"stats":"{\"numRecords\":2,\"minValues\":{\"id\":1,\"value\":\"a\"},\"maxValues\":{\"id\":2,\"value\":\"b\"},\"nullCount\":{\"id\":0,\"value\":0},\"tightBounds\":true}","tags":{"INSERTION_TIME":"1773117753348000","MIN_INSERTION_TIME":"1773117753348000","MAX_INSERTION_TIME":"1773117753348000","OPTIMIZE_TARGET_SIZE":"268435456"}}}
