{"commitInfo":{"timestamp":1773117985135,"operation":"SET TBLPROPERTIES","operationParameters":{"properties":"{\"delta.enableTypeWidening\":\"true\"}"},"readVersion":0,"isolationLevel":"WriteSerializable","isBlindAppend":true,"operationMetrics":{},"engineInfo":"Databricks-Runtime/<unknown>","txnId":"6d696af1-ddf6-4782-9bc0-504fd489d045"}}
{"metaData":{"id":"290c40e4-a21e-4340-8316-d5bada366c4b","format":{"provider":"parquet","options":{}},"schemaString":"{\"type\":\"struct\",\"fields\":[{\"name\":\"id\",\"type\":\"integer\",\"nullable\":true,\"metadata\":{}},{\"name\":\"amount\",\"type\":\"integer\",\"nullable\":true,\"metadata\":{}}]}","partitionColumns":[],"configuration":{"delta.enableDeletionVectors":"true","delta.enableTypeWidening":"true"},"createdTime":1773117984432}}
{"protocol":{"minReaderVersion":3,"minWriterVersion":7,"readerFeatures":["deletionVectors","typeWidening"],"writerFeatures":["deletionVectors","typeWidening","appendOnly","invariants"]}}
