{"commitInfo":{"timestamp":1773117191298,"operation":"WRITE","operationParameters":{"mode":"Append","statsOnLoad":false,"partitionBy":"[]"},"readVersion":0,"isolationLevel":"WriteSerializable","isBlindAppend":true,"operationMetrics":{"numFiles":"2","numOutputRows":"4","numOutputBytes":"1975"},"tags":{"noRowsCopied":"true","restoresDeletedRows":"false"},"engineInfo":"Databricks-Runtime/<unknown>","txnId":"5ab73db7-90ef-470b-b12b-9c01f0b3c0cd"}}
{"add":{"path":"year=2023/test%25file%25prefix-part-00000-f1449471-0cf4-46df-94b3-49575491cc94.c000.snappy.parquet","partitionValues":{"year":"2023"},"size":988,"modificationTime":1773117191156,"dataChange":true,"stats":"{\"numRecords\":2,\"minValues\":{\"date_col\":\"2023-06-15\",\"value\":10},\"maxValues\":{\"date_col\":\"2023-12-25\",\"value\":40},\"nullCount\":{\"date_col\":0,\"value\":0},\"tightBounds\":true}","tags":{"INSERTION_TIME":"1773117191156000","MIN_INSERTION_TIME":"1773117191156000","MAX_INSERTION_TIME":"1773117191156000","OPTIMIZE_TARGET_SIZE":"268435456"}}}
{"add":{"path":"year=2024/test%25file%25prefix-part-00000-2f98f775-fd24-4faf-8001-a95953f8a1ac.c000.snappy.parquet","partitionValues":{"year":"2024"},"size":987,"modificationTime":1773117191188,"dataChange":true,"stats":"{\"numRecords\":2,\"minValues\":{\"date_col\":\"2024-03-20\",\"value\":20},\"maxValues\":{\"date_col\":\"2024-11-01\",\"value\":30},\"nullCount\":{\"date_col\":0,\"value\":0},\"tightBounds\":true}","tags":{"INSERTION_TIME":"1773117191156001","MIN_INSERTION_TIME":"1773117191156001","MAX_INSERTION_TIME":"1773117191156001","OPTIMIZE_TARGET_SIZE":"268435456"}}}
