{"commitInfo":{"timestamp":1773119611911,"operation":"WRITE","operationParameters":{"mode":"Append","statsOnLoad":false,"partitionBy":"[]"},"readVersion":4,"isolationLevel":"WriteSerializable","isBlindAppend":true,"operationMetrics":{"numFiles":"1","numOutputRows":"1","numOutputBytes":"729"},"tags":{"noRowsCopied":"true","restoresDeletedRows":"false"},"engineInfo":"Databricks-Runtime/<unknown>","txnId":"2cb6cc14-d36c-4dd4-80e2-914762915e19"}}
{"add":{"path":"test%25file%25prefix-part-00000-437e88d9-42b2-4eb1-b4e3-7f0ca8a84585-c000.snappy.parquet","partitionValues":{},"size":729,"modificationTime":1773119611845,"dataChange":true,"stats":"{\"numRecords\":1,\"minValues\":{\"id\":4,\"value\":\"val_4\"},\"maxValues\":{\"id\":4,\"value\":\"val_4\"},\"nullCount\":{\"id\":0,\"value\":0},\"tightBounds\":true}","tags":{"INSERTION_TIME":"1773119611845000","MIN_INSERTION_TIME":"1773119611845000","MAX_INSERTION_TIME":"1773119611845000","OPTIMIZE_TARGET_SIZE":"268435456"}}}
