{"add":{"path":"test%25file%25prefix-part-00000-17e7f878-acba-4c96-89e3-d72e3353a453-c000.snappy.parquet","partitionValues":{},"size":470,"modificationTime":1773115337483,"dataChange":false,"stats":"{\"numRecords\":1,\"minValues\":{\"id\":19},\"maxValues\":{\"id\":19},\"nullCount\":{\"id\":0},\"tightBounds\":true}","tags":{"INSERTION_TIME":"1773115337483000","MIN_INSERTION_TIME":"1773115337483000","MAX_INSERTION_TIME":"1773115337483000","OPTIMIZE_TARGET_SIZE":"268435456"}}}
{"add":{"path":"test%25file%25prefix-part-00000-30ba3ac9-23fb-43af-8cf0-eab55755893b-c000.snappy.parquet","partitionValues":{},"size":470,"modificationTime":1773115334935,"dataChange":false,"stats":"{\"numRecords\":1,\"minValues\":{\"id\":15},\"maxValues\":{\"id\":15},\"nullCount\":{\"id\":0},\"tightBounds\":true}","tags":{"INSERTION_TIME":"1773115334935000","MIN_INSERTION_TIME":"1773115334935000","MAX_INSERTION_TIME":"1773115334935000","OPTIMIZE_TARGET_SIZE":"268435456"}}}
{"add":{"path":"test%25file%25prefix-part-00000-3f67aaad-86bc-4634-96bb-c281d9ea2596-c000.snappy.parquet","partitionValues":{},"size":469,"modificationTime":1773115334227,"dataChange":false,"stats":"{\"numRecords\":1,\"minValues\":{\"id\":14},\"maxValues\":{\"id\":14},\"nullCount\":{\"id\":0},\"tightBounds\":true}","tags":{"INSERTION_TIME":"1773115334227000","MIN_INSERTION_TIME":"1773115334227000","MAX_INSERTION_TIME":"1773115334227000","OPTIMIZE_TARGET_SIZE":"268435456"}}}
{"add":{"path":"test%25file%25prefix-part-00000-57cdfa92-afae-4ceb-aa4b-0b09b5bdc68d-c000.snappy.parquet","partitionValues":{},"size":470,"modificationTime":1773115335559,"dataChange":false,"stats":"{\"numRecords\":1,\"minValues\":{\"id\":16},\"maxValues\":{\"id\":16},\"nullCount\":{\"id\":0},\"tightBounds\":true}","tags":{"INSERTION_TIME":"1773115335559000","MIN_INSERTION_TIME":"1773115335559000","MAX_INSERTION_TIME":"1773115335559000","OPTIMIZE_TARGET_SIZE":"268435456"}}}
{"add":{"path":"test%25file%25prefix-part-00000-66b8e1fd-3758-40c3-935d-70c043606e2f-c000.snappy.parquet","partitionValues":{},"size":470,"modificationTime":1773115336199,"dataChange":false,"stats":"{\"numRecords\":1,\"minValues\":{\"id\":17},\"maxValues\":{\"id\":17},\"nullCount\":{\"id\":0},\"tightBounds\":true}","tags":{"INSERTION_TIME":"1773115336199000","MIN_INSERTION_TIME":"1773115336199000","MAX_INSERTION_TIME":"1773115336199000","OPTIMIZE_TARGET_SIZE":"268435456"}}}
{"add":{"path":"test%25file%25prefix-part-00000-8b40ca7c-55d0-4208-9df2-755c1d27947a-c000.snappy.parquet","partitionValues":{},"size":470,"modificationTime":1773115336843,"dataChange":false,"stats":"{\"numRecords\":1,\"minValues\":{\"id\":18},\"maxValues\":{\"id\":18},\"nullCount\":{\"id\":0},\"tightBounds\":true}","tags":{"INSERTION_TIME":"1773115336843000","MIN_INSERTION_TIME":"1773115336843000","MAX_INSERTION_TIME":"1773115336843000","OPTIMIZE_TARGET_SIZE":"268435456"}}}
