{
  "name" : "se_drop_column",
  "description" : "Read after column drop with column mapping",
  "schema" : {
    "type" : "struct",
    "fields" : [ {
      "name" : "id",
      "type" : "integer",
      "nullable" : true,
      "metadata" : {
        "delta.columnMapping.id" : 1,
        "delta.columnMapping.physicalName" : "col-3e9cfd60-384a-4fd1-9e19-c7e6f53e98fb"
      }
    }, {
      "name" : "name",
      "type" : "string",
      "nullable" : true,
      "metadata" : {
        "delta.columnMapping.id" : 2,
        "delta.columnMapping.physicalName" : "col-49fb8052-55e3-4540-a830-560e35cefafa"
      }
    } ]
  },
  "protocol" : {
    "minReaderVersion" : 3,
    "minWriterVersion" : 7,
    "readerFeatures" : [ "columnMapping", "deletionVectors" ],
    "writerFeatures" : [ "appendOnly", "changeDataFeed", "checkConstraints", "columnMapping", "deletionVectors", "generatedColumns", "invariants" ]
  },
  "logInfo" : {
    "numAddFiles" : 3,
    "numRemoveFiles" : 0,
    "sizeInBytes" : 4504,
    "numCommits" : 5,
    "numActions" : 11,
    "lastCheckpointVersion" : -1,
    "lastCrcVersion" : 4,
    "numParallelCheckpointFiles" : 0
  },
  "properties" : {
    "delta.enableDeletionVectors" : "true",
    "delta.columnMapping.mode" : "name",
    "delta.columnMapping.maxColumnId" : "3"
  },
  "dataLayout" : {
    "numClusteringColumns" : 0,
    "numPartitionColumns" : 0,
    "numDistinctPartitions" : 0
  },
  "tags" : [ "schemaEvolution" ]
}