{"commitInfo":{"timestamp":1773119590382,"operation":"WRITE","operationParameters":{"mode":"Append","statsOnLoad":false,"partitionBy":"[]"},"readVersion":10,"isolationLevel":"WriteSerializable","isBlindAppend":true,"operationMetrics":{"numFiles":"1","numOutputRows":"1","numOutputBytes":"1226"},"tags":{"noRowsCopied":"true","restoresDeletedRows":"false"},"engineInfo":"Databricks-Runtime/<unknown>","txnId":"02797da3-098e-4c2e-85d7-c38b45bb646f"}}
{"add":{"path":"og/test%25file%25prefix-part-00000-ca4b510b-7a23-41e4-b052-8ab866f0e76c-c000.snappy.parquet","partitionValues":{},"size":1226,"modificationTime":1773119590313,"dataChange":true,"stats":"{\"numRecords\":1,\"minValues\":{\"col-98619642-3e66-4e1a-ac54-8ff678c39ec3\":10,\"col-beb5c772-86f3-40ed-9ac8-cc6ccc26aa2d\":\"val_10\"},\"maxValues\":{\"col-98619642-3e66-4e1a-ac54-8ff678c39ec3\":10,\"col-beb5c772-86f3-40ed-9ac8-cc6ccc26aa2d\":\"val_10\"},\"nullCount\":{\"col-98619642-3e66-4e1a-ac54-8ff678c39ec3\":0,\"col-beb5c772-86f3-40ed-9ac8-cc6ccc26aa2d\":0},\"tightBounds\":true}","tags":{"INSERTION_TIME":"1773119590313000","MIN_INSERTION_TIME":"1773119590313000","MAX_INSERTION_TIME":"1773119590313000","OPTIMIZE_TARGET_SIZE":"268435456"}}}
