{"commitInfo":{"timestamp":1773119242624,"operation":"WRITE","operationParameters":{"mode":"Append","statsOnLoad":false,"partitionBy":"[]"},"readVersion":0,"isolationLevel":"WriteSerializable","isBlindAppend":true,"operationMetrics":{"numFiles":"1","numOutputRows":"4","numOutputBytes":"1263"},"tags":{"noRowsCopied":"true","restoresDeletedRows":"false"},"engineInfo":"Databricks-Runtime/<unknown>","txnId":"3caf1173-2265-40d2-9a0d-67b6586dd90e"}}
{"add":{"path":"test%25file%25prefix-part-00000-bf8c81b3-ad85-47f2-a3e4-c4ae1a2386a0-c000.snappy.parquet","partitionValues":{},"size":1263,"modificationTime":1773119242550,"dataChange":true,"stats":"{\"numRecords\":4,\"minValues\":{\"id\":1,\"category\":\"A\"},\"maxValues\":{\"id\":4,\"category\":\"C\"},\"nullCount\":{\"id\":0,\"category\":0,\"data\":0},\"tightBounds\":true}","tags":{"MAX_INSERTION_TIME":"1773119242550000","INSERTION_TIME":"1773119242550000","SHREDDING_STATE":"0","MIN_INSERTION_TIME":"1773119242550000","OPTIMIZE_TARGET_SIZE":"268435456"}}}
