{"commitInfo":{"timestamp":1773117153173,"operation":"CREATE TABLE","operationParameters":{"partitionBy":"[]","clusterBy":"[]","description":null,"isManaged":"false","properties":"{\"delta.enableDeletionVectors\":\"true\"}","statsOnLoad":false},"isolationLevel":"WriteSerializable","isBlindAppend":true,"operationMetrics":{},"tags":{"restoresDeletedRows":"false"},"engineInfo":"Databricks-Runtime/<unknown>","txnId":"7eb4ee48-4c95-40b8-8694-0d1df195bda0"}}
{"metaData":{"id":"ef9aa03b-7836-4600-8ef1-f55fee4eff14","format":{"provider":"parquet","options":{}},"schemaString":"{\"type\":\"struct\",\"fields\":[{\"name\":\"id\",\"type\":\"long\",\"nullable\":true,\"metadata\":{}},{\"name\":\"doubled\",\"type\":\"long\",\"nullable\":true,\"metadata\":{\"delta.generationExpression\":\"id * 2\"}}]}","partitionColumns":[],"configuration":{"delta.enableDeletionVectors":"true"},"createdTime":1773117153097}}
{"protocol":{"minReaderVersion":3,"minWriterVersion":7,"readerFeatures":["deletionVectors"],"writerFeatures":["deletionVectors","generatedColumns","appendOnly","invariants"]}}
